plugp100/__init__.py
plugp100/example.py
plugp100/api/__init__.py
plugp100/api/light_effect.py
plugp100/api/light_effect_preset.py
plugp100/api/tapo_client.py
plugp100/api/requests/__init__.py
plugp100/api/requests/handshake_params.py
plugp100/api/requests/login_device.py
plugp100/api/requests/secure_passthrough_params.py
plugp100/api/requests/tapo_request.py
plugp100/api/requests/trigger_logs_params.py
plugp100/api/requests/internal/__init__.py
plugp100/api/requests/internal/snowflake_id.py
plugp100/api/requests/set_device_info/__init__.py
plugp100/api/requests/set_device_info/play_alarm_params.py
plugp100/api/requests/set_device_info/set_light_color_info_params.py
plugp100/api/requests/set_device_info/set_light_info_params.py
plugp100/api/requests/set_device_info/set_plug_info_params.py
plugp100/api/requests/set_device_info/set_trv_info_params.py
plugp100/common/__init__.py
plugp100/common/credentials.py
plugp100/common/functional/__init__.py
plugp100/common/functional/tri.py
plugp100/common/utils/__init__.py
plugp100/common/utils/http_client.py
plugp100/common/utils/json_utils.py
plugp100/discovery/__init__.py
plugp100/discovery/cloud_client.py
plugp100/discovery/discovered_device.py
plugp100/discovery/rsa_session.py
plugp100/discovery/tapo_discovery.py
plugp100/encryption/__init__.py
plugp100/encryption/helpers.py
plugp100/encryption/key_pair.py
plugp100/encryption/tp_link_cipher.py
plugp100/new/__init__.py
plugp100/new/device_factory.py
plugp100/new/device_type.py
plugp100/new/hub_device_tracker.py
plugp100/new/tapobulb.py
plugp100/new/tapodevice.py
plugp100/new/tapohub.py
plugp100/new/tapoplug.py
plugp100/new/child/__init__.py
plugp100/new/child/tapohubchildren.py
plugp100/new/child/tapostripsocket.py
plugp100/new/components/__init__.py
plugp100/new/components/alarm_component.py
plugp100/new/components/battery_component.py
plugp100/new/components/countdown.py
plugp100/new/components/device_component.py
plugp100/new/components/energy_component.py
plugp100-5.1.5.dist-info/licenses/LICENSE
plugp100-5.1.5.dist-info/METADATA
plugp100-5.1.5.dist-info/WHEEL
plugp100-5.1.5.dist-info/top_level.txt
plugp100-5.1.5.dist-info/RECORD
