Metadata-Version: 2.4
Name: plugp100
Version: 5.1.5
Summary: Controller for TP-Link Tapo P100 and other devices
Home-page: https://github.com/petretiandrea/plugp100
Download-URL: https://github.com/petretiandrea/plugp100
Author: @petretiandrea
Author-email: petretiandrea@gmail.com
License: GPL3
Keywords: Tapo,P100
Classifier: Development Status :: 5 - Production/Stable
License-File: LICENSE
Requires-Dist: certifi>=2021.5.30
Requires-Dist: jsons>=1.6.3
Requires-Dist: requests>=2.27.1
Requires-Dist: aiohttp>=3.8.1
Requires-Dist: semantic-version==2.10.0
Requires-Dist: cryptography>=38.0.3
Requires-Dist: scapy>=2.5.0
Requires-Dist: urllib3<3,>=2.5
Dynamic: author
Dynamic: author-email
Dynamic: classifier
Dynamic: description
Dynamic: description-content-type
Dynamic: download-url
Dynamic: home-page
Dynamic: keywords
Dynamic: license
Dynamic: license-file
Dynamic: requires-dist
Dynamic: summary
